chainsyncer/backend.py
chainsyncer/driver.py
chainsyncer/error.py
chainsyncer/filter.py
chainsyncer/db/__init__.py
chainsyncer/db/migrations/sqlalchemy.py
chainsyncer/db/models/base.py
chainsyncer/db/models/filter.py
chainsyncer/db/models/sync.py
chainsyncer/runnable/tracker.py
chainsyncer-0.0.1a18.dist-info/LICENSE.txt
chainsyncer-0.0.1a18.dist-info/METADATA
chainsyncer-0.0.1a18.dist-info/WHEEL
chainsyncer-0.0.1a18.dist-info/top_level.txt
chainsyncer-0.0.1a18.dist-info/RECORD
