Metadata-Version: 2.1
Name: chainsyncer
Version: 0.0.1a18
Summary: Generic blockchain syncer driver
Home-page: https://gitlab.com/nolash/chainsyncer
Author: Louis Holbrook
Author-email: dev@holbrook.no
License: GPL3
Keywords: cryptocurrency
Platform: UNKNOWN
Classifier: Programming Language :: Python :: 3
Classifier: Operating System :: OS Independent
Classifier: Development Status :: 3 - Alpha
Classifier: Environment :: Console
Classifier: Intended Audience :: Developers
Classifier: License :: OSI Approved :: GNU General Public License v3 or later (GPLv3+)
Classifier: Topic :: Internet
Requires-Python: >=3.6
Requires-Dist: psycopg2 (==2.8.6)
Requires-Dist: SQLAlchemy (==1.3.20)
Requires-Dist: confini (~=0.3.6b2)
Requires-Dist: semver (==2.13.0)
Requires-Dist: hexathon (~=0.0.1a3)
Requires-Dist: chainlib (~=0.0.1a18)
